sapphirerenderer/__init__.py
sapphirerenderer/src/__init__.py
sapphirerenderer/src/sapphirerenderer/__init__.py
sapphirerenderer/src/sapphirerenderer/main.py
sapphirerenderer/src/sapphirerenderer/settings.py
sapphirerenderer/src/sapphirerenderer/examples/__init__.py
sapphirerenderer/src/sapphirerenderer/examples/orbit_example.py
sapphirerenderer/src/sapphirerenderer/object_classes/__init__.py
sapphirerenderer/src/sapphirerenderer/object_classes/base_object.py
sapphirerenderer/src/sapphirerenderer/object_classes/flat_faces_object.py
sapphirerenderer/src/sapphirerenderer/object_classes/text_object.py
sapphirerenderer/src/sapphirerenderer/object_classes/wireframe_object.py
sapphirerenderer/src/sapphirerenderer/objects/__init__.py
sapphirerenderer/src/sapphirerenderer/objects/axes.py
sapphirerenderer/src/sapphirerenderer/objects/cube.py
sapphirerenderer/src/sapphirerenderer/objects/cuboid.py
sapphirerenderer/src/sapphirerenderer/objects/fcube.py
sapphirerenderer/src/sapphirerenderer/objects/fobj.py
sapphirerenderer/src/sapphirerenderer/objects/fsphere.py
sapphirerenderer/src/sapphirerenderer/objects/fstl.py
sapphirerenderer/src/sapphirerenderer/objects/line.py
sapphirerenderer/src/sapphirerenderer/objects/pyramid.py
sapphirerenderer/src/sapphirerenderer/objects/sphere.py
sapphirerenderer/src/sapphirerenderer/objects/stl_.py
sapphirerenderer/src/sapphirerenderer/objects/text.py
sapphirerenderer/src/sapphirerenderer/objects/torus.py
sapphirerenderer/src/sapphirerenderer/objects/vector.py
sapphirerenderer/src/sapphirerenderer/point_math/__init__.py
sapphirerenderer/src/sapphirerenderer/point_math/average_points.py
sapphirerenderer/src/sapphirerenderer/point_math/matricies.py
sapphirerenderer/src/sapphirerenderer/point_math/project_point.py
sapphirerenderer/src/sapphirerenderer/utility_objects/__init__.py
sapphirerenderer/src/sapphirerenderer/utility_objects/camera.py
sapphirerenderer/src/sapphirerenderer/utility_objects/particle_manager.py
sapphire_renderer-0.0.53.dist-info/METADATA
sapphire_renderer-0.0.53.dist-info/WHEEL
sapphire_renderer-0.0.53.dist-info/top_level.txt
sapphire_renderer-0.0.53.dist-info/RECORD
