Metadata-Version: 2.1
Name: sapphire-renderer
Version: 0.0.53
Summary: A package to easily render simple 3D scenes
Home-page: https://github.com/DarkEden-coding/Sapphire-Renderer
Author: Dark_Eden
Author-email: darkedenc9@gmail.com
Classifier: Programming Language :: Python :: 3
Classifier: License :: OSI Approved :: MIT License
Classifier: Operating System :: OS Independent
Requires-Python: >=3.7
Requires-Dist: numpy
Requires-Dist: numba
Requires-Dist: pygame
Requires-Dist: setuptools
Requires-Dist: pywavefront
Requires-Dist: numpy-stl
